[{"line":1,"elements":[{"start_timestamp":"2025-05-26T08:29:46.686Z","before":[{"result":{"duration":9013319488,"status":"passed"},"match":{"location":"uiAutomation.stepDefinitions.Hooks.before()"}}],"line":15,"name":"User can adds an item to the cart","description":"","id":"add-to-cart;user-can-adds-an-item-to-the-cart;;2","after":[{"result":{"duration":75779985,"status":"passed"},"match":{"location":"uiAutomation.stepDefinitions.Hooks.after(io.cucumber.java.Scenario)"}}],"type":"scenario","keyword":"Scenario Outline","steps":[{"result":{"duration":145166467,"status":"passed"},"line":4,"name":"demoblaze homepage","match":{"location":"uiAutomation.stepDefinitions.SignUp.demoblaze_homepage()"},"keyword":"Given "},{"result":{"duration":188427131,"status":"passed"},"line":5,"name":"user click log in","match":{"location":"uiAutomation.stepDefinitions.Login.userClickLogin()"},"keyword":"When "},{"result":{"duration":647350726,"status":"passed"},"line":6,"name":"user input shevanr as usernameLogin","match":{"arguments":[{"val":"shevanr","offset":11}],"location":"uiAutomation.stepDefinitions.Login.userInputUsernameloginAsUsername(java.lang.String)"},"keyword":"And "},{"result":{"duration":62894455,"status":"passed"},"line":7,"name":"user input *Demoblaze99 as passwordLogin","match":{"arguments":[{"val":"*Demoblaze99","offset":11}],"location":"uiAutomation.stepDefinitions.Login.userInputPasswordloginAsPassword(java.lang.String)"},"keyword":"And "},{"result":{"duration":65389768,"status":"passed"},"line":8,"name":"user click log in button","match":{"location":"uiAutomation.stepDefinitions.Login.userClickLogInButton()"},"keyword":"And "},{"result":{"duration":545847077,"status":"passed"},"line":9,"name":"user can see welcome with username","match":{"location":"uiAutomation.stepDefinitions.Login.userCanSeeWelcomeWithUsername()"},"keyword":"Then "},{"result":{"duration":1292531973,"status":"passed"},"line":10,"name":"user add \"Samsung galaxy s6\" with ID \"1\" to the cart","match":{"arguments":[{"val":"\"Samsung galaxy s6\"","offset":9},{"val":"\"1\"","offset":37}],"location":"uiAutomation.stepDefinitions.AddtoCart.userAddProductToCart(java.lang.String,java.lang.String)"},"keyword":"When "},{"result":{"duration":692515,"status":"passed"},"line":11,"name":"user should see Samsung galaxy s6 in the cart","match":{"arguments":[{"val":"Samsung galaxy s6","offset":16}],"location":"uiAutomation.stepDefinitions.AddtoCart.userShouldSeeProductNameInTheCart(java.lang.String)"},"keyword":"Then "}],"tags":[{"name":"@web"}]},{"start_timestamp":"2025-05-26T08:29:58.752Z","before":[{"result":{"duration":632277119,"status":"passed"},"match":{"location":"uiAutomation.stepDefinitions.Hooks.before()"}}],"line":16,"name":"User can adds an item to the cart","description":"","id":"add-to-cart;user-can-adds-an-item-to-the-cart;;3","after":[{"result":{"duration":71500709,"status":"passed"},"match":{"location":"uiAutomation.stepDefinitions.Hooks.after(io.cucumber.java.Scenario)"}}],"type":"scenario","keyword":"Scenario Outline","steps":[{"result":{"duration":80418904,"status":"passed"},"line":4,"name":"demoblaze homepage","match":{"location":"uiAutomation.stepDefinitions.SignUp.demoblaze_homepage()"},"keyword":"Given "},{"result":{"duration":130582023,"status":"passed"},"line":5,"name":"user click log in","match":{"location":"uiAutomation.stepDefinitions.Login.userClickLogin()"},"keyword":"When "},{"result":{"duration":577251037,"status":"passed"},"line":6,"name":"user input shevanr as usernameLogin","match":{"arguments":[{"val":"shevanr","offset":11}],"location":"uiAutomation.stepDefinitions.Login.userInputUsernameloginAsUsername(java.lang.String)"},"keyword":"And "},{"result":{"duration":54118071,"status":"passed"},"line":7,"name":"user input *Demoblaze99 as passwordLogin","match":{"arguments":[{"val":"*Demoblaze99","offset":11}],"location":"uiAutomation.stepDefinitions.Login.userInputPasswordloginAsPassword(java.lang.String)"},"keyword":"And "},{"result":{"duration":64860367,"status":"passed"},"line":8,"name":"user click log in button","match":{"location":"uiAutomation.stepDefinitions.Login.userClickLogInButton()"},"keyword":"And "},{"result":{"duration":544523968,"status":"passed"},"line":9,"name":"user can see welcome with username","match":{"location":"uiAutomation.stepDefinitions.Login.userCanSeeWelcomeWithUsername()"},"keyword":"Then "},{"result":{"duration":1806085786,"status":"passed"},"line":10,"name":"user add \"Nokia lumia 1520\" with ID \"2\" to the cart","match":{"arguments":[{"val":"\"Nokia lumia 1520\"","offset":9},{"val":"\"2\"","offset":36}],"location":"uiAutomation.stepDefinitions.AddtoCart.userAddProductToCart(java.lang.String,java.lang.String)"},"keyword":"When "},{"result":{"duration":211756,"status":"passed"},"line":11,"name":"user should see Nokia lumia 1520 in the cart","match":{"arguments":[{"val":"Nokia lumia 1520","offset":16}],"location":"uiAutomation.stepDefinitions.AddtoCart.userShouldSeeProductNameInTheCart(java.lang.String)"},"keyword":"Then "}],"tags":[{"name":"@web"}]},{"start_timestamp":"2025-05-26T08:30:02.723Z","before":[{"result":{"duration":517784473,"status":"passed"},"match":{"location":"uiAutomation.stepDefinitions.Hooks.before()"}}],"line":17,"name":"User can adds an item to the cart","description":"","id":"add-to-cart;user-can-adds-an-item-to-the-cart;;4","after":[{"result":{"duration":72992023,"status":"passed"},"match":{"location":"uiAutomation.stepDefinitions.Hooks.after(io.cucumber.java.Scenario)"}}],"type":"scenario","keyword":"Scenario Outline","steps":[{"result":{"duration":84289859,"status":"passed"},"line":4,"name":"demoblaze homepage","match":{"location":"uiAutomation.stepDefinitions.SignUp.demoblaze_homepage()"},"keyword":"Given "},{"result":{"duration":93167421,"status":"passed"},"line":5,"name":"user click log in","match":{"location":"uiAutomation.stepDefinitions.Login.userClickLogin()"},"keyword":"When "},{"result":{"duration":581773798,"status":"passed"},"line":6,"name":"user input shevanr as usernameLogin","match":{"arguments":[{"val":"shevanr","offset":11}],"location":"uiAutomation.stepDefinitions.Login.userInputUsernameloginAsUsername(java.lang.String)"},"keyword":"And "},{"result":{"duration":51981164,"status":"passed"},"line":7,"name":"user input *Demoblaze99 as passwordLogin","match":{"arguments":[{"val":"*Demoblaze99","offset":11}],"location":"uiAutomation.stepDefinitions.Login.userInputPasswordloginAsPassword(java.lang.String)"},"keyword":"And "},{"result":{"duration":63778865,"status":"passed"},"line":8,"name":"user click log in button","match":{"location":"uiAutomation.stepDefinitions.Login.userClickLogInButton()"},"keyword":"And "},{"result":{"duration":543046922,"status":"passed"},"line":9,"name":"user can see welcome with username","match":{"location":"uiAutomation.stepDefinitions.Login.userCanSeeWelcomeWithUsername()"},"keyword":"Then "},{"result":{"duration":1278958380,"status":"passed"},"line":10,"name":"user add \"Nexus 6\" with ID \"3\" to the cart","match":{"arguments":[{"val":"\"Nexus 6\"","offset":9},{"val":"\"3\"","offset":27}],"location":"uiAutomation.stepDefinitions.AddtoCart.userAddProductToCart(java.lang.String,java.lang.String)"},"keyword":"When "},{"result":{"duration":193482,"status":"passed"},"line":11,"name":"user should see Nexus 6 in the cart","match":{"arguments":[{"val":"Nexus 6","offset":16}],"location":"uiAutomation.stepDefinitions.AddtoCart.userShouldSeeProductNameInTheCart(java.lang.String)"},"keyword":"Then "}],"tags":[{"name":"@web"}]}],"name":"Add to Cart","description":"","id":"add-to-cart","keyword":"Feature","uri":"file:src/test/resources/uiAutomation/features/addtocart.feature","tags":[]},{"line":1,"elements":[{"start_timestamp":"2025-05-26T08:30:06.018Z","before":[{"result":{"duration":486992960,"status":"passed"},"match":{"location":"uiAutomation.stepDefinitions.Hooks.before()"}}],"line":20,"name":"User can checkout after adding products to cart","description":"","id":"checkout;user-can-checkout-after-adding-products-to-cart;;2","after":[{"result":{"duration":71450604,"status":"passed"},"match":{"location":"uiAutomation.stepDefinitions.Hooks.after(io.cucumber.java.Scenario)"}}],"type":"scenario","keyword":"Scenario Outline","steps":[{"result":{"duration":80388903,"status":"passed"},"line":4,"name":"demoblaze homepage","match":{"location":"uiAutomation.stepDefinitions.SignUp.demoblaze_homepage()"},"keyword":"Given "},{"result":{"duration":98943753,"status":"passed"},"line":5,"name":"user click log in","match":{"location":"uiAutomation.stepDefinitions.Login.userClickLogin()"},"keyword":"When "},{"result":{"duration":583874297,"status":"passed"},"line":6,"name":"user input shevanr as usernameLogin","match":{"arguments":[{"val":"shevanr","offset":11}],"location":"uiAutomation.stepDefinitions.Login.userInputUsernameloginAsUsername(java.lang.String)"},"keyword":"And "},{"result":{"duration":53064211,"status":"passed"},"line":7,"name":"user input *Demoblaze99 as passwordLogin","match":{"arguments":[{"val":"*Demoblaze99","offset":11}],"location":"uiAutomation.stepDefinitions.Login.userInputPasswordloginAsPassword(java.lang.String)"},"keyword":"And "},{"result":{"duration":63219146,"status":"passed"},"line":8,"name":"user click log in button","match":{"location":"uiAutomation.stepDefinitions.Login.userClickLogInButton()"},"keyword":"And "},{"result":{"duration":540859010,"status":"passed"},"line":9,"name":"user can see welcome with username","match":{"location":"uiAutomation.stepDefinitions.Login.userCanSeeWelcomeWithUsername()"},"keyword":"Then "},{"result":{"duration":1280390324,"status":"passed"},"line":10,"name":"user add \"Samsung galaxy s6\" with ID \"1\" to the cart","match":{"arguments":[{"val":"\"Samsung galaxy s6\"","offset":9},{"val":"\"1\"","offset":37}],"location":"uiAutomation.stepDefinitions.AddtoCart.userAddProductToCart(java.lang.String,java.lang.String)"},"keyword":"When "},{"result":{"duration":178476238,"status":"passed"},"line":11,"name":"user goes to the cart","match":{"location":"uiAutomation.stepDefinitions.CheckoutSteps.userGoesToTheCart()"},"keyword":"And "},{"result":{"duration":1133613270,"status":"passed"},"line":12,"name":"user completes checkout with random details","match":{"location":"uiAutomation.stepDefinitions.CheckoutSteps.userCompletesCheckout()"},"keyword":"And "},{"result":{"duration":77604907,"status":"passed"},"line":13,"name":"user click purchase button","match":{"location":"uiAutomation.stepDefinitions.CheckoutSteps.userClickPurchaseButton()"},"keyword":"And "},{"result":{"duration":22709902,"status":"passed"},"line":14,"name":"order should be successful","match":{"location":"uiAutomation.stepDefinitions.CheckoutSteps.orderShouldBeSuccessful()"},"keyword":"Then "},{"result":{"duration":710631961,"status":"passed"},"line":15,"name":"user confirm modal success purchase","match":{"location":"uiAutomation.stepDefinitions.CheckoutSteps.userConfirmModalSuccessPurchase()"},"keyword":"And "}],"tags":[{"name":"@web"}]}],"name":"Checkout","description":"","id":"checkout","keyword":"Feature","uri":"file:src/test/resources/uiAutomation/features/checkout.feature","tags":[]},{"line":1,"elements":[{"start_timestamp":"2025-05-26T08:30:11.413Z","before":[{"result":{"duration":493866814,"status":"passed"},"match":{"location":"uiAutomation.stepDefinitions.Hooks.before()"}}],"line":19,"name":"","description":"","id":"send-message-via-contact-modal;;;2","after":[{"result":{"duration":71745922,"status":"passed"},"match":{"location":"uiAutomation.stepDefinitions.Hooks.after(io.cucumber.java.Scenario)"}}],"type":"scenario","keyword":"Scenario Outline","steps":[{"result":{"duration":75491028,"status":"passed"},"line":4,"name":"demoblaze homepage","match":{"location":"uiAutomation.stepDefinitions.SignUp.demoblaze_homepage()"},"keyword":"Given "},{"result":{"duration":86314163,"status":"passed"},"line":5,"name":"user click log in","match":{"location":"uiAutomation.stepDefinitions.Login.userClickLogin()"},"keyword":"When "},{"result":{"duration":580832712,"status":"passed"},"line":6,"name":"user input shevanr as usernameLogin","match":{"arguments":[{"val":"shevanr","offset":11}],"location":"uiAutomation.stepDefinitions.Login.userInputUsernameloginAsUsername(java.lang.String)"},"keyword":"And "},{"result":{"duration":54815454,"status":"passed"},"line":7,"name":"user input *Demoblaze99 as passwordLogin","match":{"arguments":[{"val":"*Demoblaze99","offset":11}],"location":"uiAutomation.stepDefinitions.Login.userInputPasswordloginAsPassword(java.lang.String)"},"keyword":"And "},{"result":{"duration":64117463,"status":"passed"},"line":8,"name":"user click log in button","match":{"location":"uiAutomation.stepDefinitions.Login.userClickLogInButton()"},"keyword":"And "},{"result":{"duration":541777568,"status":"passed"},"line":9,"name":"user can see welcome with username","match":{"location":"uiAutomation.stepDefinitions.Login.userCanSeeWelcomeWithUsername()"},"keyword":"Then "},{"result":{"duration":62872707,"status":"passed"},"line":10,"name":"user click contact","match":{"location":"uiAutomation.stepDefinitions.ContactMessage.userClickLogin()"},"keyword":"When "},{"result":{"duration":608500290,"status":"passed"},"line":11,"name":"user input \"random\" as contact email","match":{"arguments":[{"val":"\"random\"","offset":11}],"location":"uiAutomation.stepDefinitions.ContactMessage.userInputContactEmail(java.lang.String)"},"keyword":"And "},{"result":{"duration":66977707,"status":"passed"},"line":12,"name":"user input \"random\" as contact name","match":{"arguments":[{"val":"\"random\"","offset":11}],"location":"uiAutomation.stepDefinitions.ContactMessage.userInputContactName(java.lang.String)"},"keyword":"And "},{"result":{"duration":143481602,"status":"passed"},"line":13,"name":"user input \"random\" contact message","match":{"arguments":[{"val":"\"random\"","offset":11}],"location":"uiAutomation.stepDefinitions.ContactMessage.userInputContactMessage(java.lang.String)"},"keyword":"And "},{"result":{"duration":78621736,"status":"passed"},"line":14,"name":"user click send message","match":{"location":"uiAutomation.stepDefinitions.ContactMessage.userClickSendMessage()"},"keyword":"And "},{"result":{"duration":27228952,"status":"passed"},"line":15,"name":"will show success send message Thanks for the message!! as success message","match":{"arguments":[{"val":"Thanks for the message!!","offset":31}],"location":"uiAutomation.stepDefinitions.ContactMessage.willShowSuccessSendMessage(java.lang.String)"},"keyword":"Then "}],"tags":[{"name":"@web"}]}],"name":"Send Message via Contact Modal","description":"","id":"send-message-via-contact-modal","keyword":"Feature","uri":"file:src/test/resources/uiAutomation/features/contact.feature","tags":[]},{"line":1,"elements":[{"start_timestamp":"2025-05-26T08:30:14.378Z","before":[{"result":{"duration":486707150,"status":"passed"},"match":{"location":"uiAutomation.stepDefinitions.Hooks.before()"}}],"line":21,"name":"User completes a end-to-end journey from login-checkout-logout","description":"","id":"end-to-end-test-for-user-journey;user-completes-a-end-to-end-journey-from-login-checkout-logout;;2","after":[{"result":{"duration":70201360,"status":"passed"},"match":{"location":"uiAutomation.stepDefinitions.Hooks.after(io.cucumber.java.Scenario)"}}],"type":"scenario","keyword":"Scenario Outline","steps":[{"result":{"duration":80768870,"status":"passed"},"line":4,"name":"demoblaze homepage","match":{"location":"uiAutomation.stepDefinitions.SignUp.demoblaze_homepage()"},"keyword":"Given "},{"result":{"duration":89854072,"status":"passed"},"line":5,"name":"user click log in","match":{"location":"uiAutomation.stepDefinitions.Login.userClickLogin()"},"keyword":"When "},{"result":{"duration":579507359,"status":"passed"},"line":6,"name":"user input shevanr as usernameLogin","match":{"arguments":[{"val":"shevanr","offset":11}],"location":"uiAutomation.stepDefinitions.Login.userInputUsernameloginAsUsername(java.lang.String)"},"keyword":"And "},{"result":{"duration":51099162,"status":"passed"},"line":7,"name":"user input *Demoblaze99 as passwordLogin","match":{"arguments":[{"val":"*Demoblaze99","offset":11}],"location":"uiAutomation.stepDefinitions.Login.userInputPasswordloginAsPassword(java.lang.String)"},"keyword":"And "},{"result":{"duration":62393780,"status":"passed"},"line":8,"name":"user click log in button","match":{"location":"uiAutomation.stepDefinitions.Login.userClickLogInButton()"},"keyword":"And "},{"result":{"duration":539391254,"status":"passed"},"line":9,"name":"user can see welcome with username","match":{"location":"uiAutomation.stepDefinitions.Login.userCanSeeWelcomeWithUsername()"},"keyword":"Then "},{"result":{"duration":170291242,"status":"passed"},"line":10,"name":"user goes to the cart","match":{"location":"uiAutomation.stepDefinitions.CheckoutSteps.userGoesToTheCart()"},"keyword":"And "},{"result":{"duration":979511549,"status":"passed"},"line":11,"name":"user completes checkout with random details","match":{"location":"uiAutomation.stepDefinitions.CheckoutSteps.userCompletesCheckout()"},"keyword":"And "},{"result":{"duration":65717606,"status":"passed"},"line":12,"name":"user click purchase button","match":{"location":"uiAutomation.stepDefinitions.CheckoutSteps.userClickPurchaseButton()"},"keyword":"And "},{"result":{"duration":24489189,"status":"passed"},"line":13,"name":"order should be successful","match":{"location":"uiAutomation.stepDefinitions.CheckoutSteps.orderShouldBeSuccessful()"},"keyword":"Then "},{"result":{"duration":713428779,"status":"passed"},"line":14,"name":"user confirm modal success purchase","match":{"location":"uiAutomation.stepDefinitions.CheckoutSteps.userConfirmModalSuccessPurchase()"},"keyword":"And "},{"result":{"duration":24144294,"status":"passed"},"line":15,"name":"user see logout menu","match":{"location":"uiAutomation.stepDefinitions.Logout.userSeeLogoutMenu()"},"keyword":"And "},{"result":{"duration":150920757,"status":"passed"},"line":16,"name":"user click logout","match":{"location":"uiAutomation.stepDefinitions.Logout.userClickLogout()"},"keyword":"And "},{"result":{"duration":45899939,"status":"passed"},"line":17,"name":"user successfully logout","match":{"location":"uiAutomation.stepDefinitions.Logout.userSuccessfullyLogout()"},"keyword":"Then "}],"tags":[{"name":"@web"}]}],"name":"End-to-End Test for User Journey","description":"","id":"end-to-end-test-for-user-journey","keyword":"Feature","uri":"file:src/test/resources/uiAutomation/features/endtoendjourney.feature","tags":[]},{"line":1,"elements":[{"start_timestamp":"2025-05-26T08:30:18.521Z","before":[{"result":{"duration":501708931,"status":"passed"},"match":{"location":"uiAutomation.stepDefinitions.Hooks.before()"}}],"line":13,"name":"User can login to Demoblaze","description":"","id":"login-to-demoblaze;user-can-login-to-demoblaze;;2","after":[{"result":{"duration":69685197,"status":"passed"},"match":{"location":"uiAutomation.stepDefinitions.Hooks.after(io.cucumber.java.Scenario)"}}],"type":"scenario","keyword":"Scenario Outline","steps":[{"result":{"duration":57254165,"status":"passed"},"line":4,"name":"demoblaze homepage","match":{"location":"uiAutomation.stepDefinitions.SignUp.demoblaze_homepage()"},"keyword":"Given "},{"result":{"duration":107405210,"status":"passed"},"line":5,"name":"user click log in","match":{"location":"uiAutomation.stepDefinitions.Login.userClickLogin()"},"keyword":"When "},{"result":{"duration":586263853,"status":"passed"},"line":6,"name":"user input shevanr as usernameLogin","match":{"arguments":[{"val":"shevanr","offset":11}],"location":"uiAutomation.stepDefinitions.Login.userInputUsernameloginAsUsername(java.lang.String)"},"keyword":"And "},{"result":{"duration":53562254,"status":"passed"},"line":7,"name":"user input *Demoblaze99 as passwordLogin","match":{"arguments":[{"val":"*Demoblaze99","offset":11}],"location":"uiAutomation.stepDefinitions.Login.userInputPasswordloginAsPassword(java.lang.String)"},"keyword":"And "},{"result":{"duration":64529419,"status":"passed"},"line":8,"name":"user click log in button","match":{"location":"uiAutomation.stepDefinitions.Login.userClickLogInButton()"},"keyword":"And "},{"result":{"duration":539288581,"status":"passed"},"line":9,"name":"user can see welcome with username","match":{"location":"uiAutomation.stepDefinitions.Login.userCanSeeWelcomeWithUsername()"},"keyword":"Then "}],"tags":[{"name":"@web"}]}],"name":"Login to Demoblaze","description":"","id":"login-to-demoblaze","keyword":"Feature","uri":"file:src/test/resources/uiAutomation/features/login.feature","tags":[]},{"line":1,"elements":[{"start_timestamp":"2025-05-26T08:30:20.507Z","before":[{"result":{"duration":493550470,"status":"passed"},"match":{"location":"uiAutomation.stepDefinitions.Hooks.before()"}}],"line":14,"name":"User cannot login to Demoblaze when the password is invalid","description":"","id":"login-to-demoblaze;user-cannot-login-to-demoblaze-when-the-password-is-invalid;;2","after":[{"result":{"duration":72550341,"status":"passed"},"match":{"location":"uiAutomation.stepDefinitions.Hooks.after(io.cucumber.java.Scenario)"}}],"type":"scenario","keyword":"Scenario Outline","steps":[{"result":{"duration":70902359,"status":"passed"},"line":5,"name":"demoblaze homepage","match":{"location":"uiAutomation.stepDefinitions.SignUp.demoblaze_homepage()"},"keyword":"Given "},{"result":{"duration":90931566,"status":"passed"},"line":6,"name":"user click log in","match":{"location":"uiAutomation.stepDefinitions.Login.userClickLogin()"},"keyword":"When "},{"result":{"duration":578175833,"status":"passed"},"line":7,"name":"user input shevanr as usernameLogin","match":{"arguments":[{"val":"shevanr","offset":11}],"location":"uiAutomation.stepDefinitions.Login.userInputUsernameloginAsUsername(java.lang.String)"},"keyword":"And "},{"result":{"duration":50228325,"status":"passed"},"line":8,"name":"user input wrongpassword as passwordLogin","match":{"arguments":[{"val":"wrongpassword","offset":11}],"location":"uiAutomation.stepDefinitions.Login.userInputPasswordloginAsPassword(java.lang.String)"},"keyword":"And "},{"result":{"duration":67903310,"status":"passed"},"line":9,"name":"user click log in button","match":{"location":"uiAutomation.stepDefinitions.Login.userClickLogInButton()"},"keyword":"And "},{"result":{"duration":532209199,"status":"passed"},"line":10,"name":"user will get Wrong password. as wrong password message","match":{"arguments":[{"val":"Wrong password.","offset":14}],"location":"uiAutomation.stepDefinitions.LoginWrongPassword.willGetWrongPasswordMessage(java.lang.String)"},"keyword":"Then "}],"tags":[{"name":"@web"}]}],"name":"Login to Demoblaze","description":"","id":"login-to-demoblaze","keyword":"Feature","uri":"file:src/test/resources/uiAutomation/features/loginwrongpassword.feature","tags":[]},{"line":1,"elements":[{"start_timestamp":"2025-05-26T08:30:22.469Z","before":[{"result":{"duration":484338705,"status":"passed"},"match":{"location":"uiAutomation.stepDefinitions.Hooks.before()"}}],"line":16,"name":"user can logout from Demoblaze","description":"","id":"logout-from-demoblaze;user-can-logout-from-demoblaze;;2","after":[{"result":{"duration":70042448,"status":"passed"},"match":{"location":"uiAutomation.stepDefinitions.Hooks.after(io.cucumber.java.Scenario)"}}],"type":"scenario","keyword":"Scenario Outline","steps":[{"result":{"duration":78732371,"status":"passed"},"line":4,"name":"demoblaze homepage","match":{"location":"uiAutomation.stepDefinitions.SignUp.demoblaze_homepage()"},"keyword":"Given "},{"result":{"duration":86125755,"status":"passed"},"line":5,"name":"user click log in","match":{"location":"uiAutomation.stepDefinitions.Login.userClickLogin()"},"keyword":"When "},{"result":{"duration":580395805,"status":"passed"},"line":6,"name":"user input shevanr as usernameLogin","match":{"arguments":[{"val":"shevanr","offset":11}],"location":"uiAutomation.stepDefinitions.Login.userInputUsernameloginAsUsername(java.lang.String)"},"keyword":"And "},{"result":{"duration":50193867,"status":"passed"},"line":7,"name":"user input *Demoblaze99 as passwordLogin","match":{"arguments":[{"val":"*Demoblaze99","offset":11}],"location":"uiAutomation.stepDefinitions.Login.userInputPasswordloginAsPassword(java.lang.String)"},"keyword":"And "},{"result":{"duration":60664412,"status":"passed"},"line":8,"name":"user click log in button","match":{"location":"uiAutomation.stepDefinitions.Login.userClickLogInButton()"},"keyword":"And "},{"result":{"duration":538166125,"status":"passed"},"line":9,"name":"user can see welcome with username","match":{"location":"uiAutomation.stepDefinitions.Login.userCanSeeWelcomeWithUsername()"},"keyword":"Then "},{"result":{"duration":123882040,"status":"passed"},"line":11,"name":"user click logout","match":{"location":"uiAutomation.stepDefinitions.Logout.userClickLogout()"},"keyword":"And "},{"result":{"duration":49257998,"status":"passed"},"line":12,"name":"user successfully logout","match":{"location":"uiAutomation.stepDefinitions.Logout.userSuccessfullyLogout()"},"keyword":"Then "}],"tags":[{"name":"@web"}]}],"name":"Logout from Demoblaze","description":"","id":"logout-from-demoblaze","keyword":"Feature","uri":"file:src/test/resources/uiAutomation/features/logout.feature","tags":[]},{"line":1,"elements":[{"start_timestamp":"2025-05-26T08:30:24.598Z","before":[{"result":{"duration":504354757,"status":"passed"},"match":{"location":"uiAutomation.stepDefinitions.Hooks.before()"}}],"line":13,"name":"User an sign up to Demoblaze","description":"","id":"sign-up-to-demoblaze;user-an-sign-up-to-demoblaze;;2","after":[{"result":{"duration":75126534,"status":"passed"},"match":{"location":"uiAutomation.stepDefinitions.Hooks.after(io.cucumber.java.Scenario)"}}],"type":"scenario","keyword":"Scenario Outline","steps":[{"result":{"duration":74995562,"status":"passed"},"line":4,"name":"demoblaze homepage","match":{"location":"uiAutomation.stepDefinitions.SignUp.demoblaze_homepage()"},"keyword":"Given "},{"result":{"duration":112985628,"status":"passed"},"line":5,"name":"user click sign up","match":{"location":"uiAutomation.stepDefinitions.SignUp.user_click_sign_up()"},"keyword":"When "},{"result":{"duration":595414953,"status":"passed"},"line":6,"name":"user input \"random\" as username","match":{"arguments":[{"val":"\"random\"","offset":11}],"location":"uiAutomation.stepDefinitions.SignUp.user_input_username_as_username(java.lang.String)"},"keyword":"And "},{"result":{"duration":50917084,"status":"passed"},"line":7,"name":"user input \"random\" as password","match":{"arguments":[{"val":"\"random\"","offset":11}],"location":"uiAutomation.stepDefinitions.SignUp.user_input_password_as_password(java.lang.String)"},"keyword":"And "},{"result":{"duration":61992879,"status":"passed"},"line":8,"name":"user click sign up button","match":{"location":"uiAutomation.stepDefinitions.SignUp.user_click_sign_up_button()"},"keyword":"And "},{"result":{"duration":534195775,"status":"passed"},"line":9,"name":"will show success sign up Sign up successful. as expected message","match":{"arguments":[{"val":"Sign up successful.","offset":26}],"location":"uiAutomation.stepDefinitions.SignUp.will_show_success_sign_up_expected_message(java.lang.String)"},"keyword":"Then "}],"tags":[{"name":"@web"}]}],"name":"Sign Up to Demoblaze","description":"","id":"sign-up-to-demoblaze","keyword":"Feature","uri":"file:src/test/resources/uiAutomation/features/signup.feature","tags":[]}]